dbbackup_git/__init__.py
dbbackup_git/apps.py
dbbackup_git/implementation.py
dbbackup_git/utils.py
dbbackup_git/management/__init__.py
dbbackup_git/management/commands/__init__.py
dbbackup_git/management/commands/dbbackup_git.py
django_database_backup_to_git-2.0.dist-info/LICENSE
django_database_backup_to_git-2.0.dist-info/METADATA
django_database_backup_to_git-2.0.dist-info/WHEEL
django_database_backup_to_git-2.0.dist-info/top_level.txt
django_database_backup_to_git-2.0.dist-info/RECORD
