Metadata-Version: 2.1
Name: django-database-backup-to-git
Version: 2.0
Summary: Django specific database backup system
Home-page: https://gitlab.com/eeriksp/django-database-backup-to-git
Author: Eerik Sven Puudist
Project-URL: Bug Tracker, https://gitlab.com/eeriksp/django-database-backup-to-git
Classifier: Programming Language :: Python :: 3
Classifier: License :: OSI Approved :: MIT License
Classifier: Operating System :: OS Independent
Requires-Python: >=3.6
License-File: LICENSE
Requires-Dist: django
